{
  "version": "2.0.3",
  "summary": {
    "title": "threat_model",
    "owner": "Piotr Frątczak",
    "description": "Microservices application for people to arrange workouts together.",
    "id": 0
  },
  "detail": {
    "contributors": [
      {
        "name": "Piotr Frątczak"
      }
    ],
    "diagrams": [
      {
        "id": 0,
        "title": "stride_diagram",
        "diagramType": "STRIDE",
        "placeholder": "New STRIDE diagram description",
        "thumbnail": "./public/content/images/thumbnail.stride.jpg",
        "version": "2.0.3",
        "cells": [
          {
            "position": {
              "x": 430,
              "y": 170
            },
            "size": {
              "width": 112.5,
              "height": 60
            },
            "attrs": {
              "text": {
                "text": "User"
              },
              "body": {
                "stroke": "#333333",
                "strokeWidth": 1,
                "strokeDasharray": null
              }
            },
            "visible": true,
            "shape": "actor",
            "id": "a893ba74-a418-4fd0-80d2-cdda51112ebd",
            "zIndex": 1,
            "data": {
              "type": "tm.Actor",
              "name": "User",
              "description": "",
              "outOfScope": false,
              "reasonOutOfScope": "",
              "providesAuthentication": false,
              "hasOpenThreats": false,
              "threats": []
            }
          },
          {
            "position": {
              "x": 730,
              "y": 90
            },
            "size": {
              "width": 70,
              "height": 70
            },
            "attrs": {
              "text": {
                "text": "Mobile\nApp"
              },
              "body": {
                "stroke": "#333333",
                "strokeWidth": 1,
                "strokeDasharray": null
              }
            },
            "visible": true,
            "shape": "process",
            "id": "06672ae9-baf5-4193-9ef1-4683f4d49359",
            "zIndex": 2,
            "data": {
              "type": "tm.Process",
              "name": "Mobile\nApp",
              "description": "",
              "outOfScope": false,
              "reasonOutOfScope": "",
              "privilegeLevel": "",
              "hasOpenThreats": false,
              "threats": []
            }
          },
          {
            "position": {
              "x": 710,
              "y": 220
            },
            "size": {
              "width": 70,
              "height": 70
            },
            "attrs": {
              "text": {
                "text": "Web\nBrowser"
              },
              "body": {
                "stroke": "#333333",
                "strokeWidth": 1,
                "strokeDasharray": null
              }
            },
            "visible": true,
            "shape": "process",
            "id": "a661a418-9ee8-4ede-a6ff-5bdf93d4a462",
            "zIndex": 3,
            "data": {
              "type": "tm.Process",
              "name": "Web\nBrowser",
              "description": "",
              "outOfScope": false,
              "reasonOutOfScope": "",
              "privilegeLevel": "",
              "hasOpenThreats": false,
              "threats": []
            }
          },
          {
            "shape": "flow",
            "attrs": {
              "line": {
                "stroke": "#333333",
                "strokeWidth": 1,
                "targetMarker": {
                  "name": "classic"
                },
                "strokeDasharray": null
              }
            },
            "width": 200,
            "height": 100,
            "zIndex": 10,
            "connector": "smooth",
            "data": {
              "type": "tm.Flow",
              "name": "Data Flow",
              "description": "",
              "outOfScope": false,
              "reasonOutOfScope": "",
              "protocol": "",
              "isEncrypted": false,
              "isPublicNetwork": false,
              "hasOpenThreats": false,
              "threats": []
            },
            "id": "2c45d8e3-8afd-41cf-bc40-3eb73045ec77",
            "source": {
              "cell": "a893ba74-a418-4fd0-80d2-cdda51112ebd"
            },
            "target": {
              "cell": "06672ae9-baf5-4193-9ef1-4683f4d49359"
            }
          },
          {
            "shape": "flow",
            "attrs": {
              "line": {
                "stroke": "#333333",
                "strokeWidth": 1,
                "targetMarker": {
                  "name": "classic"
                },
                "strokeDasharray": null
              }
            },
            "width": 200,
            "height": 100,
            "zIndex": 10,
            "connector": "smooth",
            "data": {
              "type": "tm.Flow",
              "name": "Data Flow",
              "description": "",
              "outOfScope": false,
              "reasonOutOfScope": "",
              "protocol": "",
              "isEncrypted": false,
              "isPublicNetwork": false,
              "hasOpenThreats": false,
              "threats": []
            },
            "id": "a77f31e2-8a24-4ba6-bdd6-f3b1868a71d5",
            "source": {
              "cell": "a893ba74-a418-4fd0-80d2-cdda51112ebd"
            },
            "target": {
              "cell": "a661a418-9ee8-4ede-a6ff-5bdf93d4a462"
            }
          },
          {
            "shape": "flow",
            "attrs": {
              "line": {
                "stroke": "#333333",
                "strokeWidth": 1,
                "targetMarker": {
                  "name": "classic"
                },
                "strokeDasharray": null
              }
            },
            "width": 200,
            "height": 100,
            "zIndex": 10,
            "connector": "smooth",
            "data": {
              "type": "tm.Flow",
              "name": "https",
              "description": "",
              "outOfScope": false,
              "reasonOutOfScope": "",
              "protocol": "",
              "isEncrypted": false,
              "isPublicNetwork": false,
              "hasOpenThreats": false,
              "threats": []
            },
            "id": "a7f10766-4bdb-442c-951a-4f36a1a934df",
            "source": {
              "cell": "ca2b4942-9231-4804-bcba-f0ee6917e06c"
            },
            "target": {
              "cell": "1f7e4ae6-ff06-4169-af64-a1df2202071b"
            },
            "labels": [
              "https"
            ]
          },
          {
            "shape": "flow",
            "attrs": {
              "line": {
                "stroke": "#333333",
                "strokeWidth": 1,
                "targetMarker": {
                  "name": "classic"
                },
                "strokeDasharray": null
              }
            },
            "width": 200,
            "height": 100,
            "zIndex": 10,
            "connector": "smooth",
            "data": {
              "type": "tm.Flow",
              "name": "Data Flow",
              "description": "",
              "outOfScope": false,
              "reasonOutOfScope": "",
              "protocol": "",
              "isEncrypted": false,
              "isPublicNetwork": false,
              "hasOpenThreats": false,
              "threats": []
            },
            "id": "26c1490d-4aa0-4630-81ab-91a2f178fcd4",
            "source": {
              "cell": "78eab160-8bde-4a3f-9102-78819b21d091"
            },
            "target": {
              "cell": "ca2b4942-9231-4804-bcba-f0ee6917e06c"
            }
          },
          {
            "position": {
              "x": 899,
              "y": 200
            },
            "size": {
              "width": 70,
              "height": 70
            },
            "attrs": {
              "text": {
                "text": "Web App\nServer"
              },
              "body": {
                "stroke": "#333333",
                "strokeWidth": 1,
                "strokeDasharray": null
              }
            },
            "visible": true,
            "shape": "process",
            "id": "bed16f4f-aea1-4dab-acde-f0e2c56e53cb",
            "zIndex": 11,
            "data": {
              "type": "tm.Process",
              "name": "Web App\nServer",
              "description": "",
              "outOfScope": false,
              "reasonOutOfScope": "",
              "privilegeLevel": "",
              "hasOpenThreats": false,
              "threats": []
            }
          },
          {
            "shape": "flow",
            "attrs": {
              "line": {
                "stroke": "#333333",
                "strokeWidth": 1,
                "targetMarker": {
                  "name": "classic"
                },
                "strokeDasharray": null
              }
            },
            "width": 200,
            "height": 100,
            "connector": "smooth",
            "data": {
              "type": "tm.Flow",
              "name": "https",
              "description": "",
              "outOfScope": false,
              "reasonOutOfScope": "",
              "protocol": "",
              "isEncrypted": false,
              "isPublicNetwork": false,
              "hasOpenThreats": false,
              "threats": []
            },
            "id": "93343163-7ece-424d-b4d7-e9c6df192146",
            "labels": [
              "https"
            ],
            "source": {
              "cell": "78eab160-8bde-4a3f-9102-78819b21d091"
            },
            "target": {
              "cell": "f2b2927b-2a0a-4a8c-afd1-8bd8f4598ef1"
            },
            "zIndex": 12
          },
          {
            "shape": "flow",
            "attrs": {
              "line": {
                "stroke": "#333333",
                "strokeWidth": 1,
                "targetMarker": {
                  "name": "classic"
                },
                "strokeDasharray": null
              }
            },
            "width": 200,
            "height": 100,
            "connector": "smooth",
            "data": {
              "type": "tm.Flow",
              "name": "https",
              "description": "",
              "outOfScope": false,
              "reasonOutOfScope": "",
              "protocol": "",
              "isEncrypted": false,
              "isPublicNetwork": false,
              "hasOpenThreats": false,
              "threats": []
            },
            "id": "28649c5f-d70d-4cda-baf7-699d6bd7ee7b",
            "labels": [
              "https"
            ],
            "source": {
              "cell": "bed16f4f-aea1-4dab-acde-f0e2c56e53cb"
            },
            "target": {
              "cell": "78eab160-8bde-4a3f-9102-78819b21d091"
            },
            "zIndex": 13
          },
          {
            "shape": "flow",
            "attrs": {
              "line": {
                "stroke": "#333333",
                "strokeWidth": 1,
                "targetMarker": {
                  "name": "classic"
                },
                "strokeDasharray": null
              }
            },
            "width": 200,
            "height": 100,
            "connector": "smooth",
            "data": {
              "type": "tm.Flow",
              "name": "https",
              "description": "",
              "outOfScope": false,
              "reasonOutOfScope": "",
              "protocol": "",
              "isEncrypted": false,
              "isPublicNetwork": false,
              "hasOpenThreats": false,
              "threats": []
            },
            "id": "a8bda3c1-7ed0-4046-8dd8-88edb50ad55c",
            "labels": [
              "https"
            ],
            "source": {
              "cell": "06672ae9-baf5-4193-9ef1-4683f4d49359"
            },
            "target": {
              "cell": "78eab160-8bde-4a3f-9102-78819b21d091"
            },
            "zIndex": 14
          },
          {
            "shape": "flow",
            "attrs": {
              "line": {
                "stroke": "#333333",
                "strokeWidth": 1,
                "targetMarker": {
                  "name": "classic"
                },
                "strokeDasharray": null
              }
            },
            "width": 200,
            "height": 100,
            "connector": "smooth",
            "data": {
              "type": "tm.Flow",
              "name": "https",
              "description": "",
              "outOfScope": false,
              "reasonOutOfScope": "",
              "protocol": "",
              "isEncrypted": false,
              "isPublicNetwork": false,
              "hasOpenThreats": false,
              "threats": []
            },
            "id": "4f7e69dc-e63a-4ba0-be60-dee6c68d9e39",
            "labels": [
              "https"
            ],
            "source": {
              "cell": "a661a418-9ee8-4ede-a6ff-5bdf93d4a462"
            },
            "target": {
              "cell": "bed16f4f-aea1-4dab-acde-f0e2c56e53cb"
            },
            "zIndex": 15
          },
          {
            "position": {
              "x": 1057,
              "y": 120
            },
            "size": {
              "width": 80,
              "height": 80
            },
            "attrs": {
              "text": {
                "text": "API"
              },
              "body": {
                "stroke": "#333333",
                "strokeWidth": 1,
                "strokeDasharray": null
              }
            },
            "visible": true,
            "shape": "process",
            "id": "78eab160-8bde-4a3f-9102-78819b21d091",
            "zIndex": 16,
            "data": {
              "type": "tm.Process",
              "name": "API",
              "description": "",
              "outOfScope": false,
              "reasonOutOfScope": "",
              "privilegeLevel": "",
              "hasOpenThreats": false,
              "threats": []
            }
          },
          {
            "position": {
              "x": 1090,
              "y": 280
            },
            "size": {
              "width": 100,
              "height": 100
            },
            "attrs": {
              "text": {
                "text": "Authentication\nMicroservice"
              },
              "body": {
                "stroke": "#333333",
                "strokeWidth": 1,
                "strokeDasharray": null
              }
            },
            "visible": true,
            "shape": "process",
            "id": "ca2b4942-9231-4804-bcba-f0ee6917e06c",
            "zIndex": 17,
            "data": {
              "type": "tm.Process",
              "name": "Authentication\nMicroservice",
              "description": "",
              "outOfScope": false,
              "reasonOutOfScope": "",
              "privilegeLevel": "",
              "hasOpenThreats": false,
              "threats": []
            }
          },
          {
            "position": {
              "x": 1270,
              "y": 190
            },
            "size": {
              "width": 100,
              "height": 100
            },
            "attrs": {
              "text": {
                "text": "Events\nMicroservice"
              },
              "body": {
                "stroke": "#333333",
                "strokeWidth": 1,
                "strokeDasharray": null
              }
            },
            "visible": true,
            "shape": "process",
            "id": "1c8cc1c0-22c4-4de5-909b-34269d7834b8",
            "zIndex": 18,
            "data": {
              "type": "tm.Process",
              "name": "Events\nMicroservice",
              "description": "",
              "outOfScope": false,
              "reasonOutOfScope": "",
              "privilegeLevel": "",
              "hasOpenThreats": false,
              "threats": []
            }
          },
          {
            "position": {
              "x": 1270,
              "y": 40
            },
            "size": {
              "width": 100,
              "height": 100
            },
            "attrs": {
              "text": {
                "text": "Users\nMicroservice"
              },
              "body": {
                "stroke": "#333333",
                "strokeWidth": 1,
                "strokeDasharray": null
              }
            },
            "visible": true,
            "shape": "process",
            "id": "f2b2927b-2a0a-4a8c-afd1-8bd8f4598ef1",
            "data": {
              "type": "tm.Process",
              "name": "Users\nMicroservice",
              "description": "",
              "outOfScope": false,
              "reasonOutOfScope": "",
              "privilegeLevel": "",
              "hasOpenThreats": false,
              "threats": []
            },
            "zIndex": 19
          },
          {
            "shape": "flow",
            "attrs": {
              "line": {
                "stroke": "#333333",
                "strokeWidth": 1,
                "targetMarker": {
                  "name": "classic"
                },
                "strokeDasharray": null
              }
            },
            "width": 200,
            "height": 100,
            "connector": "smooth",
            "data": {
              "type": "tm.Flow",
              "name": "",
              "description": "",
              "outOfScope": false,
              "reasonOutOfScope": "",
              "protocol": "",
              "isEncrypted": false,
              "isPublicNetwork": false,
              "hasOpenThreats": false,
              "threats": []
            },
            "id": "ac79f2e6-4ffe-4378-9320-30561e06c669",
            "labels": [
              "https"
            ],
            "source": {
              "cell": "78eab160-8bde-4a3f-9102-78819b21d091"
            },
            "target": {
              "cell": "1c8cc1c0-22c4-4de5-909b-34269d7834b8"
            },
            "zIndex": 20
          },
          {
            "position": {
              "x": 1340,
              "y": 370
            },
            "size": {
              "width": 120,
              "height": 60
            },
            "attrs": {
              "text": {
                "text": "Google Identity\nStore"
              },
              "topLine": {
                "strokeWidth": 1,
                "strokeDasharray": "5 2"
              },
              "bottomLine": {
                "strokeWidth": 1,
                "strokeDasharray": "5 2"
              }
            },
            "visible": true,
            "shape": "store",
            "id": "1f7e4ae6-ff06-4169-af64-a1df2202071b",
            "zIndex": 21,
            "data": {
              "type": "tm.Store",
              "name": "Google Identity\nStore",
              "description": "",
              "outOfScope": true,
              "reasonOutOfScope": "Managed by Google",
              "isALog": false,
              "storesCredentials": false,
              "isEncrypted": false,
              "isSigned": false,
              "hasOpenThreats": false,
              "threats": []
            }
          }
        ]
      }
    ],
    "diagramTop": 1,
    "reviewer": "",
    "threatTop": 0
  }
}